{
  "id": "EEJBHD7E",
  "name": "Sydney Adventure Package",
  "destinations": [
    {
      "name": "Sydney",
      "country": "Australia",
      "duration_days": 4
    },
    {
      "name": "Bangkok",
      "country": "Thailand",
      "duration_days": 3
    },
    {
      "name": "Tokyo",
      "country": "Japan",
      "duration_days": 5
    }
  ],
  "total_duration": 11,
  "price_usd": 1598,
  "includes": [
    "Round-trip flights",
    "Hotel accommodations",
    "Airport transfers",
    "Travel insurance",
    "24/7 support"
  ],
  "created_at": "2025-11-08T00:11:38.759Z"
}