{
  "id": "KF4BHFUG",
  "name": "Bali Adventure Package",
  "destinations": [
    {
      "name": "Bali",
      "country": "Indonesia",
      "duration_days": 5
    },
    {
      "name": "Rome",
      "country": "Italy",
      "duration_days": 2
    },
    {
      "name": "Tokyo",
      "country": "Japan",
      "duration_days": 1
    },
    {
      "name": "Paris",
      "country": "France",
      "duration_days": 7
    }
  ],
  "total_duration": 16,
  "price_usd": 3419,
  "includes": [
    "Round-trip flights",
    "Hotel accommodations",
    "Airport transfers",
    "Travel insurance",
    "24/7 support"
  ],
  "created_at": "2025-11-11T08:00:09.841Z"
}