{
  "id": "YFZM0841",
  "name": "Bali Adventure Package",
  "destinations": [
    {
      "name": "Bali",
      "country": "Indonesia",
      "duration_days": 2
    },
    {
      "name": "Barcelona",
      "country": "Spain",
      "duration_days": 3
    },
    {
      "name": "New York",
      "country": "USA",
      "duration_days": 1
    },
    {
      "name": "Dubai",
      "country": "UAE",
      "duration_days": 1
    }
  ],
  "total_duration": 22,
  "price_usd": 3263,
  "includes": [
    "Round-trip flights",
    "Hotel accommodations",
    "Airport transfers",
    "Travel insurance",
    "24/7 support"
  ],
  "created_at": "2025-11-04T00:22:25.825Z"
}